ObjectListView3/CellEditor.py
ObjectListView3/Filter.py
ObjectListView3/ListCtrlPrinter.py
ObjectListView3/OLVEvent.py
ObjectListView3/OLVPrinter.py
ObjectListView3/ObjectListView.py
ObjectListView3/WordWrapRenderer.py
ObjectListView3/__init__.py
ObjectListView3-1.3.5.dist-info/AUTHORS.txt
ObjectListView3-1.3.5.dist-info/METADATA
ObjectListView3-1.3.5.dist-info/WHEEL
ObjectListView3-1.3.5.dist-info/top_level.txt
ObjectListView3-1.3.5.dist-info/RECORD
