Metadata-Version: 2.1
Name: ObjectListView3
Version: 1.3.5
Summary: An ObjectListView is a wrapper around the wx.ListCtrl that makes the list control easier to use.
Author-email: Mike Driscoll <mike@pythonlibrary.org>
Project-URL: Homepage, https://github.com/driscollis/ObjectListView3
Project-URL: Issues, https://github.com/driscollis/ObjectListView3/issues
Classifier: Programming Language :: Python :: 3
Classifier: License :: OSI Approved :: MIT License
Classifier: Operating System :: OS Independent
Requires-Python: >=3.9
License-File: AUTHORS.txt
